codelinker/__init__.py
codelinker/config.py
codelinker/events/__init__.py
codelinker/events/processer.py
codelinker/events/sink.py
codelinker/linker.py
codelinker/models/__init__.py
codelinker/models/labels.py
codelinker/models/sink.py
codelinker/models/structuredRet.py
codelinker/request/__init__.py
codelinker/request/objGen.py
codelinker/request/openai.py
codelinker-0.3.27.dist-info/LICENSE
codelinker-0.3.27.dist-info/METADATA
codelinker-0.3.27.dist-info/WHEEL
codelinker-0.3.27.dist-info/RECORD
