Metadata-Version: 2.1
Name: codelinker
Version: 0.3.27
Summary: A tool to link the code with large language models.
Author: luyaxi
Author-email: luyaxi@live.com
Requires-Python: >=3.10,<4.0
Classifier: Programming Language :: Python :: 3
Classifier: Programming Language :: Python :: 3.10
Classifier: Programming Language :: Python :: 3.11
Classifier: Programming Language :: Python :: 3.12
Classifier: Programming Language :: Python :: 3.13
Requires-Dist: jsonschema (>=4.21.1,<5.0)
Requires-Dist: openai (>=1.16.2,<2.0)
Requires-Dist: pydantic (>=2.6)
Requires-Dist: tenacity (>=8.2.3,<10.0)
Requires-Dist: tiktoken (>=0.7.0,<1.0)
Requires-Dist: toml (>=0.10.2,<1.0)
